run_raise_cycle/__init__.py
run_raise_cycle/main.py
run_raise_cycle-1.1.1.dist-info/licenses/LICENSE
run_raise_cycle-1.1.1.dist-info/METADATA
run_raise_cycle-1.1.1.dist-info/WHEEL
run_raise_cycle-1.1.1.dist-info/entry_points.txt
run_raise_cycle-1.1.1.dist-info/top_level.txt
run_raise_cycle-1.1.1.dist-info/RECORD
