Metadata-Version: 2.4
Name: run-raise-cycle
Version: 1.1.1
Summary: Run, raise, or cycle through application windows
Author-email: "@readwithai" <talwrii@gmail.com>
License: MIT
Project-URL: Homepage, https://github.com/yourusername/run-raise-cycle
Classifier: Programming Language :: Python :: 3
Classifier: License :: OSI Approved :: MIT License
Classifier: Operating System :: POSIX :: Linux
Classifier: Environment :: X11 Applications
Requires-Python: >=3.7
License-File: LICENSE
Dynamic: license-file
